Workbook

Sheet 1. Como Usar
A1: DIAGNÓSTICO FINANCEIRO PRO — LUKANA MARCENARIA
A4: BEM-VINDO AO DIAGNÓSTICO FINANCEIRO PRO
A6: Esta planilha foi desenvolvida para você ter CLAREZA TOTAL sobre a saúde financeira da sua marcenaria.
A8: 📋 COMO USAR ESTA PLANILHA:
A10: 1️⃣ PREENCHA OS DADOS DA EMPRESA | B10: Vá para a aba '2. Dados da Empresa' e preencha nome, CNPJ e período de análise
A12: 2️⃣ REGISTRE SEU FATURAMENTO | B12: Aba '3. Faturamento 3 Meses' - digite o faturamento de cada mês
A14: 3️⃣ REGISTRE CUSTOS VARIÁVEIS | B14: Aba '4. Custos Variáveis' - material, mão de obra direta, terceirizações
A16: 4️⃣ REGISTRE CUSTOS FIXOS | B16: Aba '5. Custos Fixos' - aluguel, folha administrativa, luz, água, contador
A18: 5️⃣ ANALISE OS RESULTADOS | B18: As abas de análise calculam tudo automaticamente:
A19: • Margem de Contribuição | B19: Quanto sobra depois de pagar material e MO
A20: • Margem Líquida | B20: Quanto sobra MESMO (depois de tudo)
A21: • Identificação de Sangrias | B21: Onde você está perdendo dinheiro
A23: 6️⃣ CONSULTE O DASHBOARD | B23: Aba '11. Dashboard Visual' mostra tudo em gráficos
A25: ⚠️ CAMPOS AMARELOS = VOCÊ PREENCHE
A26: ⚠️ CAMPOS BRANCOS/CINZA = CÁLCULO AUTOMÁTICO (NÃO MEXE)
A28: ❓ TEM DÚVIDAS SOBRE OS TERMOS? | B28: Consulte a aba '12. Glossário'
A30: 💡 DICA IMPORTANTE: | B30: Preencha com dados REAIS dos últimos 3 meses. Quanto mais preciso, melhor o diagnóstico.

Sheet 2. Dados da Empresa
A1: DADOS DA EMPRESA
A3: Nome da Marcenaria:
A4: CNPJ:
A5: Cidade/Estado:
A6: Período de Análise: | B6: Últimos 3 meses

Sheet 3. Faturamento 3 Meses
A1: FATURAMENTO DOS ÚLTIMOS 3 MESES
A3: Mês | B3: Faturamento Bruto (R$) | C3: Impostos s/ Venda (%) | D3: Impostos s/ Venda (R$)
A4: Mês 1 | C4: 0.1 | D4: =B4*C4
A5: Mês 2 | C5: 0.1 | D5: =B5*C5
A6: Mês 3 | C6: 0.1 | D6: =B6*C6
A7: TOTAL | B7: =SUM(B4:B6) | D7: =SUM(D4:D6)

Sheet 4. Custos Variáveis
A1: CUSTOS VARIÁVEIS (CMV)
A3: Item | B3: Mês 1 | C3: Mês 2 | D3: Mês 3
A4: Material Direto (MDF, MDP, ferragens)
A5: Mão de Obra Direta (marceneiros)
A6: Terceirizações (pintura, vidro)
A7: Frete de Material
A8: Perda Técnica (10-15% do material)
A9: TOTAL CUSTOS VARIÁVEIS | B9: =SUM(B4:B8) | C9: =SUM(C4:C8) | D9: =SUM(D4:D8)

Sheet 5. Custos Fixos
A1: CUSTOS FIXOS (DESPESAS OPERACIONAIS)
A3: Item | B3: Mês 1 | C3: Mês 2 | D3: Mês 3
A4: Aluguel / IPTU
A5: Folha Administrativa (vendedor, assistente)
A6: Luz, Água, Internet, Telefone
A7: Contador
A8: Marketing / Anúncios
A9: Manutenção Preventiva
A10: Limpeza / Segurança
A11: Seguros
A12: Pró-labore do Dono
A13: TOTAL CUSTOS FIXOS | B13: =SUM(B4:B12) | C13: =SUM(C4:C12) | D13: =SUM(D4:D12)

Sheet 6. Análise de Margem
A1: ANÁLISE DE MARGEM
A3: Indicador | B3: Mês 1 | C3: Mês 2 | D3: Mês 3
A4: Faturamento Bruto | B4: ='3. Faturamento 3 Meses'!B4 | C4: ='3. Faturamento 3 Meses'!C4 | D4: ='3. Faturamento 3 Meses'!D4
A5: (-) Impostos | B5: ='3. Faturamento 3 Meses'!D4 | C5: ='3. Faturamento 3 Meses'!D5 | D5: ='3. Faturamento 3 Meses'!D6
A6: =Receita Líquida | B6: =B4-B5 | C6: =C4-C5 | D6: =D4-D5
A7: (-) Custos Variáveis | B7: ='4. Custos Variáveis'!B9 | C7: ='4. Custos Variáveis'!C9 | D7: ='4. Custos Variáveis'!D9
A8: =MARGEM DE CONTRIBUIÇÃO | B8: =B6-B7 | C8: =C6-C7 | D8: =D6-D7
A9: % Margem de Contribuição | B9: =B8/B4 | C9: =C8/C4 | D9: =D8/D4
A11: (-) Custos Fixos | B11: ='5. Custos Fixos'!B13 | C11: ='5. Custos Fixos'!C13 | D11: ='5. Custos Fixos'!D13
A12: =LUCRO LÍQUIDO | B12: =B8-B11 | C12: =C8-C11 | D12: =D8-D11
A13: % Margem Líquida | B13: =B12/B4 | C13: =C12/C4 | D13: =D12/D4
A16: 📊 ANÁLISE AUTOMÁTICA:
A18: Margem de Contribuição Média: | B18: =AVERAGE(B9,C9,D9)
A19: Margem Líquida Média: | B19: =AVERAGE(B13,C13,D13)
A21: Status Margem de Contribuição: | B21: =IF(B18>=0.6,"✅ EXCELENTE (60%+)",IF(B18>=0.55,"⚠️ AJUSTÁVEL (55-60%)","🔴 CRÍTICO (<55%)"))
A22: Status Margem Líquida: | B22: =IF(B19>=0.25,"✅ EXCELENTE (25%+)",IF(B19>=0.15,"⚠️ RAZOÁVEL (15-25%)","🔴 CRÍTICO (<15%)"))

Sheet 7. Identificação de Sangrias
A1: IDENTIFICAÇÃO DE SANGRIAS (ONDE VOCÊ PERDE DINHEIRO)
A3: Esta aba identifica automaticamente os 3 maiores custos (variáveis e fixos) para você atacar primeiro.
A5: 🔴 TOP 3 CUSTOS VARIÁVEIS (média dos 3 meses)
A7: Item | B7: Média Mensal | C7: % do Faturamento
A8: Material Direto | B8: =AVERAGE('4. Custos Variáveis'!B4:D4) | C8: =B8/AVERAGE('3. Faturamento 3 Meses'!B4:D4)
A9: Mão de Obra Direta | B9: =AVERAGE('4. Custos Variáveis'!B5:D5) | C9: =B9/AVERAGE('3. Faturamento 3 Meses'!B4:D4)
A10: Perda Técnica | B10: =AVERAGE('4. Custos Variáveis'!B8:D8) | C10: =B10/AVERAGE('3. Faturamento 3 Meses'!B4:D4)
A13: 🔴 TOP 3 CUSTOS FIXOS (média dos 3 meses)
A15: Item | B15: Média Mensal | C15: % do Faturamento
A16: Folha Administrativa | B16: =AVERAGE('5. Custos Fixos'!B5:D5) | C16: =B16/AVERAGE('3. Faturamento 3 Meses'!B4:D4)
A17: Pró-labore do Dono | B17: =AVERAGE('5. Custos Fixos'!B12:D12) | C17: =B17/AVERAGE('3. Faturamento 3 Meses'!B4:D4)
A18: Aluguel / IPTU | B18: =AVERAGE('5. Custos Fixos'!B4:D4) | C18: =B18/AVERAGE('3. Faturamento 3 Meses'!B4:D4)
A21: 💡 RECOMENDAÇÕES:
A23: ✅ Material Direto alto? → Negocie com fornecedor, compare preços, otimize corte
A24: ✅ Mão de Obra alta? → Valide se você tá precificando certo (fator de complexidade)
A25: ✅ Perda Técnica alta? → Use software de corte, crie checklist de validação
A26: ✅ Folha Administrativa alta? → Valide se todos são necessários, pode terceirizar algo?
A27: ✅ Pró-labore alto? → Ajuste conforme faturamento (8-12% do faturamento é razoável)

Sheet 8. Fluxo de Caixa
A1: FLUXO DE CAIXA (PROJEÇÃO 6 MESES)
A3: Item | B3: Mês 1 | C3: Mês 2 | D3: Mês 3 | E3: Mês 4 | F3: Mês 5 | G3: Mês 6
A4: Saldo Inicial | C4: =B13 | D4: =C13 | E4: =D13 | F4: =E13 | G4: =F13
A5: + Faturamento Recebido
A6: - Material
A7: - Mão de Obra
A8: - Custos Fixos
A9: - Impostos
A10: =Total Saídas | B10: =SUM(B6:B9) | C10: =SUM(C6:C9) | D10: =SUM(D6:D9) | E10: =SUM(E6:E9) | F10: =SUM(F6:F9) | G10: =SUM(G6:G9)
A12: =Resultado do Mês | B12: =B5-B10 | C12: =C5-C10 | D12: =D5-D10 | E12: =E5-E10 | F12: =F5-F10 | G12: =G5-G10
A13: =SALDO FINAL | B13: =B4+B12 | C13: =C4+C12 | D13: =D4+D12 | E13: =E4+E12 | F13: =F4+F12 | G13: =G4+G12

Sheet 9. DRE Gerencial
A1: DRE GERENCIAL (DEMONSTRAÇÃO DO RESULTADO DO EXERCÍCIO)
A4: (+) FATURAMENTO BRUTO | B4: ='3. Faturamento 3 Meses'!B7
A6: (-) DEDUÇÕES
A7: Impostos sobre venda | B7: ='3. Faturamento 3 Meses'!D7
A9: (=) RECEITA LÍQUIDA | B9: =B4-B7
A11: (-) CUSTOS VARIÁVEIS (CMV)
A12: Material + MO + Terceirizações | B12: ='4. Custos Variáveis'!B9
A14: (=) MARGEM DE CONTRIBUIÇÃO | B14: =B9-B12
A15: % Margem de Contribuição | B15: =B14/B4
A17: (-) CUSTOS FIXOS
A18: Despesas Operacionais | B18: ='5. Custos Fixos'!B13
A20: (=) EBITDA | B20: =B14-B18
A21: % EBITDA | B21: =B21/B4
A23: (-) CUSTOS FINANCEIROS
A24: Juros + Taxas Bancárias | B24: 0
A26: (-) PRÓ-LABORE DO DONO
A27: Retirada do Gestor | B27: ='5. Custos Fixos'!B12
A29: (=) LUCRO LÍQUIDO REAL | B29: =B21-B25-B29
A30: % Margem Líquida | B30: =B32/B4

Sheet 10. Projeções
A1: PROJEÇÕES (3 CENÁRIOS)
A3: Com base nos dados dos últimos 3 meses, aqui estão 3 cenários de projeção:
A5: Cenário | B5: Faturamento Mês 4 | C5: Margem Líquida | D5: Lucro Estimado
A6: 🔴 PESSIMISTA (-10%) | B6: =AVERAGE('3. Faturamento 3 Meses'!B4:D4)*0.9 | C6: ='6. Análise de Margem'!B19*0.9 | D6: =B6*C6
A7: 🟡 REALISTA (média) | B7: =AVERAGE('3. Faturamento 3 Meses'!B4:D4) | C7: ='6. Análise de Margem'!B19 | D7: =B7*C7
A8: 🟢 OTIMISTA (+20%) | B8: =AVERAGE('3. Faturamento 3 Meses'!B4:D4)*1.2 | C8: ='6. Análise de Margem'!B19*1.1 | D8: =B8*C8

Sheet 11. Dashboard Visual
A1: 📊 DASHBOARD EXECUTIVO
A3: FATURAMENTO MÉDIO | D3: MARGEM CONTRIBUIÇÃO | G3: MARGEM LÍQUIDA
A6: 📈 Evolução de Faturamento (3 meses)
A8: Mês | B8: Faturamento
A9: Mês 1 | B9: ='3. Faturamento 3 Meses'!B4
A10: Mês 2 | B10: ='3. Faturamento 3 Meses'!B5
A11: Mês 3 | B11: ='3. Faturamento 3 Meses'!B6
A13: 💡 ANÁLISE RÁPIDA:
A15: Status Geral: | B15: =IF('6. Análise de Margem'!B19>=0.25,"✅ Lucratividade saudável",IF('6. Análise de Margem'!B19>=0.15,"⚠️ Margem apertada","🔴 Situação crítica"))
A16: Tendência: | B16: =IF('3. Faturamento 3 Meses'!D4>'3. Faturamento 3 Meses'!B4,"📈 Crescendo","📉 Caindo")
A17: Ação Imediata: | B17: "Revisar os 3 maiores custos (aba Sangrias)"

Sheet 12. Glossário
A1: 📖 GLOSSÁRIO DE TERMOS FINANCEIROS
A3: Termo | B3: O que significa
A4: Faturamento Bruto | B4: Total de vendas realizadas no mês (mesmo que ainda não tenha recebido)
A5: Receita Líquida | B5: Faturamento bruto menos impostos sobre vendas
A6: Custos Variáveis (CMV) | B6: Custos que variam conforme a produção: material, mão de obra direta, terceirizações
A7: Margem de Contribuição | B7: Quanto sobra depois de pagar material e mão de obra. Ideal: 60-70%
A8: Custos Fixos | B8: Custos que você paga todo mês, produzindo ou não: aluguel, folha, luz, contador
A9: EBITDA | B9: Lucro operacional antes de juros e impostos não-operacionais
A10: Lucro Líquido | B10: Quanto sobra MESMO depois de pagar absolutamente tudo (incluindo pró-labore)
A11: Margem Líquida | B11: Lucro líquido dividido pelo faturamento. Ideal: 25-35%
A12: Ponto de Equilíbrio | B12: Quanto você precisa faturar no mínimo pra não ter prejuízo (nem lucro, nem perda)
A13: Fluxo de Caixa | B13: Entradas e saídas de dinheiro mês a mês. Mostra se você vai ter dinheiro no banco
A14: DRE | B14: Demonstração do Resultado: mostra de onde vem e pra onde vai cada centavo
... A16: Perda Técnica | B16: Material que se perde no processo (sobra de corte, erro, refugo). Média: 10-15%
