Workbook

Sheet 1. Como Usar
A1: PRECIFICAÇÃO AVANÇADA PRO — LUKANA MARCENARIA
A4: BEM-VINDO À CALCULADORA DE PRECIFICAÇÃO PRO
A6: Esta planilha calcula o preço ideal de cada projeto com MARGEM GARANTIDA de 35%.
A8: 📋 COMO USAR:
A10: 1️⃣ CONFIGURE SEUS DADOS BASE | B10: Aba '2. Dados Base' - custos de material, MO, perda técnica, margem desejada
A11: 2️⃣ USE A CALCULADORA | B11: Aba '3. Calculadora' - digite tamanho do projeto e complexidade → preço sai automaticamente
A12: 3️⃣ SIMULE CENÁRIOS | B12: Aba '4. Simulador' - veja como mudanças de margem/material impactam o preço final
A13: 4️⃣ CONSULTE TABELA DE REFERÊNCIA | B13: Aba '5. Tabela Referência' - preços por m² frontal de cada tipo de móvel
A14: 5️⃣ REGISTRE ORÇAMENTOS | B14: Aba '6. Histórico' - guarde todos os orçamentos feitos
A16: ⚠️ CAMPOS AMARELOS = VOCÊ PREENCHE
A17: ⚠️ CAMPOS CINZA = CÁLCULO AUTOMÁTICO
A19: 💡 FATOR DE COMPLEXIDADE:
A20: • Simples (1.0) = Armário reto, sem gaveta, sem LED
A21: • Médio (1.3) = Cozinha padrão com gavetas
A22: • Alto (1.6) = Closet com gavetas internas + LED
A23: • Muito Alto (2.0) = Móvel curvo, laca, design especial

Sheet 2. Dados Base
A1: DADOS BASE DE PRECIFICAÇÃO
A3: 📦 CUSTOS DE MATERIAL (por m² real)
A4: Material | B4: Custo/m² (R$)
A5: MDF Branco 18mm | B5: 120
A6: MDF Amadeirado 18mm | B6: 140
A7: MDP Branco 18mm | B7: 90
A8: MDP Amadeirado 18mm | B8: 100
A10: 👷 MÃO DE OBRA
A12: Custo MO por m² real (padrão simples): | B12: 90
A15: ⚙️ PARÂMETROS DE CÁLCULO
A17: Perda Técnica (%): | B17: 0.15 | C17: 15% do material
A18: Conversão m² frontal → m² real: | B18: 2.46 | C18: Multiplicador padrão indústria
A19: Margem mínima desejada (%): | B19: 0.35 | C19: 35% de lucro
A20: Custo fixo diluído médio (R$): | B20: 2000 | C20: Por projeto médio

Sheet 3. Calculadora
A1: 🧮 CALCULADORA DE PREÇO
A3: 📝 DADOS DO PROJETO
A5: Tamanho (m² frontais): | B5: 8
A6: Material escolhido: | B6: MDF Branco 18mm
A7: Complexidade: | B7: 1.3
A10: 💰 CÁLCULO AUTOMÁTICO
A12: m² reais (frontal × 2,46): | B12: =B5*'2. Dados Base'!B18
A13: Custo material bruto: | B13: =B12*'2. Dados Base'!B5
A14: + Perda técnica (15%): | B14: =B13*0.15
A15: =Material REAL: | B15: =B13+B14
A16: Custo MO: | B16: =B12*'2. Dados Base'!B12*B7
A17: Custo fixo diluído: | B17: ='2. Dados Base'!B20
A18: =CUSTO TOTAL: | B18: =B15+B16+B17
A19: Margem desejada (35%): | B19: ='2. Dados Base'!B19
A20: =PREÇO FINAL: | B20: =B18/(1-B19)
A21: Preço por m² frontal: | B21: =B20/B5
A25: ✅ VALIDAÇÃO: | B25: =IF(B19>=0.35,"✅ Margem OK (35%+)","⚠️ Margem abaixo do ideal")

Sheet 4. Simulador
A1: 🔄 SIMULADOR DE CENÁRIOS
A3: Veja como mudanças de margem, material ou MO impactam o preço final
A5: Cenário | B5: Margem (%) | C5: Custo Material | D5: Custo MO | E5: Preço Final | F5: Diferença
A6: BASE (35% margem) | B6: 0.35 | C6: ='3. Calculadora'!B15 | D6: ='3. Calculadora'!B16 | E6: =(C6+D6+'2. Dados Base'!B20)/(1-B6)
A7: Margem Agressiva (40%) | B7: 0.4 | C7: ='3. Calculadora'!B15 | D7: ='3. Calculadora'!B16 | E7: =(C7+D7+'2. Dados Base'!B20)/(1-B7) | F7: =E7-$E$6
A8: Margem Mínima (30%) | B8: 0.3 | C8: ='3. Calculadora'!B15 | D8: ='3. Calculadora'!B16 | E8: =(C8+D8+'2. Dados Base'!B20)/(1-B8) | F8: =E8-$E$6
A9: Material Premium (+20%) | B9: 0.35 | C9: ='3. Calculadora'!B15*1.2 | D9: ='3. Calculadora'!B16 | E9: =(C9+D9+'2. Dados Base'!B20)/(1-B9) | F9: =E9-$E$6
A10: Material Econômico (-15%) | B10: 0.35 | C10: ='3. Calculadora'!B15*0.85 | D10: ='3. Calculadora'!B16 | E10: =(C10+D10+'2. Dados Base'!B20)/(1-B10) | F10: =E10-$E$6

Sheet 5. Tabela Referência
A1: 📊 TABELA DE PREÇOS DE REFERÊNCIA
A3: Preços sugeridos por m² frontal (baseado em margem de 35%)
A5: Tipo de Móvel | B5: Complexidade | C5: Preço/m² Frontal | D5: Exemplo 8m²
A6: Armário Simples | B6: Baixa (1.0) | C6: 1400 | D6: 11200
A7: Guarda-roupa Padrão | B7: Média (1.3) | C7: 1700 | D7: 13600
A8: Cozinha Completa | B8: Média-Alta (1.4) | C8: 2000 | D8: 16000
A9: Closet Básico | B9: Alta (1.6) | C9: 2400 | D9: 19200
A10: Home Office | B10: Média-Alta (1.5) | C10: 2200 | D10: 17600
A11: Banheiro Planejado | B11: Muito Alta (1.8) | C11: 2600 | D11: 20800
A13: 💡 Como usar esta tabela:
A14: 1. Cliente pede orçamento de cozinha de 10m² → você já sabe: R$ 2.000/m² × 10 = R$ 20.000 (estimativa rápida)

Sheet 6. Histórico
A1: 📋 HISTÓRICO DE ORÇAMENTOS
A3: Data | B3: Cliente | C3: Tipo Móvel | D3: m² Frontal | E3: Preço Orçado | F3: Status | G3: Preço/m² | H3: Margem %
A4: 15/04/2025 | B4: João Silva | C4: Cozinha | D4: 10 | E4: 20000 | F4: Fechado | G4: =E4/D4 | H4: 0.35
A5: 18/04/2025 | B5: Maria Santos | C5: Closet | D5: 12 | E5: 28800 | F5: Pendente | G5: =E5/D5 | H5: 0.35
A7: ESTATÍSTICAS:
A9: Total de Orçamentos: | B9: =COUNTA(B4:B100)
A10: Ticket Médio: | B10: =AVERAGE(E4:E100)
A11: Taxa de Conversão: | B11: =COUNTIF(F4:F100,"Fechado")/COUNTA(F4:F100)
